crcFinder/__init__.py
crcFinder/__main__.py
crcFinder/calculator.py
crcFinder/finder.py
crcFinder/solver.py
crcfinder-0.0.4.dist-info/METADATA
crcfinder-0.0.4.dist-info/WHEEL
crcfinder-0.0.4.dist-info/licenses/LICENSE
crcfinder-0.0.4.dist-info/RECORD
