Metadata-Version: 2.4
Name: crcFinder
Version: 0.0.4
Summary: A tool to find well known crc params that matches the input data and crc result (right or wrong)
Project-URL: Homepage, https://github.com/leommxj/crcFinder
Author-email: leommxj <leommxj@gmail.com>
License-File: LICENSE
Classifier: License :: OSI Approved :: GNU General Public License v3 (GPLv3)
Classifier: Operating System :: OS Independent
Classifier: Programming Language :: Python :: 3
Requires-Python: >=3.7
